pg2cf/__init__.py
pg2cf/pg2cf.py
pg2cf-1.0.2.dist-info/DESCRIPTION.rst
pg2cf-1.0.2.dist-info/METADATA
pg2cf-1.0.2.dist-info/RECORD
pg2cf-1.0.2.dist-info/WHEEL
pg2cf-1.0.2.dist-info/entry_points.txt
pg2cf-1.0.2.dist-info/metadata.json
pg2cf-1.0.2.dist-info/top_level.txt
