Metadata-Version: 2.0
Name: pg2cf
Version: 1.0.2
Summary: Performs PostgresSQL dumps and stashes them in CloudFiles
Home-page: https://github.com/getstatusy/pg2cf
Author: Lev Lazinskiy
Author-email: lev@levlaz.org
License: MIT
Keywords: backup cloud database
Platform: UNKNOWN
Classifier: Development Status :: 5 - Production/Stable
Classifier: Environment :: Console
Classifier: Intended Audience :: System Administrators
Classifier: License :: OSI Approved :: MIT License
Classifier: Operating System :: OS Independent
Classifier: Programming Language :: Python :: 2.7
Classifier: Topic :: System :: Archiving :: Backup
Requires-Dist: python-cloudfiles (==1.7.11)
Provides-Extra: test
Requires-Dist: coverage; extra == 'test'
Requires-Dist: flake8; extra == 'test'
Requires-Dist: xmlrunner; extra == 'test'
